Metadata-Version: 1.0
Name: udacity-test-package-noel
Version: 0.1
Summary: Gaussian distributions
Home-page: UNKNOWN
Author: Noel Markham
Author-email: nmarkham96@gmail.com
License: UNKNOWN
Platform: UNKNOWN
